peach2slack.py
peachapisec_slack-1.5.41.dist-info/METADATA
peachapisec_slack-1.5.41.dist-info/WHEEL
peachapisec_slack-1.5.41.dist-info/entry_points.txt
peachapisec_slack-1.5.41.dist-info/top_level.txt
peachapisec_slack-1.5.41.dist-info/RECORD
