Metadata-Version: 2.1
Name: peachapisec-slack
Version: 1.5.41
Summary: Peach API Security Slack Notifications
Home-page: https://peach.tech
Author: Peach Tech
Author-email: contact@peach.tech
License: Apache License, Version 2.0
Keywords: peach fuzzing security test rest
Platform: UNKNOWN
Classifier: Development Status :: 5 - Production/Stable
Classifier: Intended Audience :: Developers
Classifier: License :: OSI Approved :: Apache Software License
Classifier: Operating System :: OS Independent
Classifier: Topic :: Security
Classifier: Topic :: Software Development :: Quality Assurance
Classifier: Topic :: Software Development :: Testing
Classifier: Topic :: Utilities
Classifier: Programming Language :: Python
Classifier: Programming Language :: Python :: 2
Classifier: Programming Language :: Python :: 3
Requires-Dist: click (~=6.7)
Requires-Dist: peachapisec-api (==1.5.41)
Requires-Dist: requests (>=2.18.4)
Requires-Dist: pystache
